{
  "count": 5,
  "players": [
    {
      "username": "Firestorm3050",
      "steam_id": "76561198031138505",
      "connected_at": "28-12-25 18:17:59.587",
      "x": 10364,
      "y": 12673,
      "z": 0,
      "online": true
    },
    {
      "username": "lefons",
      "steam_id": "76561199121326240",
      "connected_at": "28-12-25 18:27:25.676",
      "x": 6245,
      "y": 5333,
      "z": 0,
      "online": true
    },
    {
      "username": "KeenIslander",
      "steam_id": "76561199122629737",
      "connected_at": "28-12-25 18:58:27.655",
      "x": 12543,
      "y": 4263,
      "z": 0,
      "online": true
    },
    {
      "username": "squibby",
      "steam_id": "76561199249031770",
      "connected_at": "28-12-25 18:39:15.286",
      "x": 10638,
      "y": 10628,
      "z": 0,
      "online": true
    },
    {
      "username": "CaptainLobo",
      "steam_id": "76561198044597580",
      "connected_at": "28-12-25 18:50:15.019",
      "x": 1899,
      "y": 14456,
      "z": 0,
      "online": true
    }
  ],
  "timestamp": "2025-12-28T19:05:01.642021"
}