{
  "count": 4,
  "players": [
    {
      "username": "Sully",
      "steam_id": "76561198119296623",
      "connected_at": "27-12-25 19:54:57.275",
      "x": 10052,
      "y": 8251,
      "z": 0,
      "online": true
    },
    {
      "username": "Firestorm3050",
      "steam_id": "76561198031138505",
      "connected_at": "27-12-25 20:11:32.347",
      "x": 10659,
      "y": 9571,
      "z": 0,
      "online": true
    },
    {
      "username": "Zero",
      "steam_id": "76561198060886931",
      "connected_at": "27-12-25 19:21:52.843",
      "x": 8606,
      "y": 8826,
      "z": 0,
      "online": true
    },
    {
      "username": "CaptainLobo",
      "steam_id": "76561198044597580",
      "connected_at": "27-12-25 20:00:34.058",
      "x": 5717,
      "y": 5723,
      "z": 0,
      "online": true
    }
  ],
  "timestamp": "2025-12-27T20:35:01.149475"
}