{
  "count": 4,
  "players": [
    {
      "username": "Sully",
      "steam_id": "76561198119296623",
      "connected_at": "23-12-25 00:07:02.866",
      "x": 10101,
      "y": 8241,
      "z": 0,
      "online": true
    },
    {
      "username": "Woofie",
      "steam_id": "76561198864938417",
      "connected_at": "23-12-25 02:47:14.582",
      "x": 10100,
      "y": 8241,
      "z": 0,
      "online": true
    },
    {
      "username": "Kessel",
      "steam_id": "76561199251232344",
      "connected_at": "23-12-25 03:58:06.211",
      "x": 11907,
      "y": 6939,
      "z": 0,
      "online": true
    },
    {
      "username": "Pabstlite",
      "steam_id": "76561198419791953",
      "connected_at": "23-12-25 03:35:15.565",
      "x": 11915,
      "y": 6951,
      "z": 0,
      "online": true
    }
  ],
  "timestamp": "2025-12-23T04:00:01.435175"
}