{
  "user_events": [
    {
      "timestamp": "19-12-25 07:50:35.341",
      "steam_id": "76561198065774641",
      "username": "BetoJin",
      "action": "fully connected",
      "x": "10109",
      "y": "8240",
      "z": "0"
    },
    {
      "timestamp": "19-12-25 07:51:14.714",
      "steam_id": "76561198065774641",
      "username": "BetoJin",
      "action": "disconnected",
      "x": "10110",
      "y": "8240",
      "z": "0"
    },
    {
      "timestamp": "19-12-25 15:09:03.016",
      "steam_id": "76561198014472311",
      "username": "SOBS",
      "action": "attempting to join"
    },
    {
      "timestamp": "19-12-25 15:09:03.016",
      "steam_id": "76561198014472311",
      "username": "SOBS",
      "action": "allowed to join"
    },
    {
      "timestamp": "19-12-25 15:09:22.383",
      "steam_id": "76561198014472311",
      "username": "SOBS",
      "action": "attempting to join"
    },
    {
      "timestamp": "19-12-25 15:10:20.060",
      "steam_id": "76561198014472311",
      "username": "SOBS",
      "action": "fully connected",
      "x": "10083",
      "y": "8255",
      "z": "1"
    },
    {
      "timestamp": "19-12-25 16:05:19.299",
      "steam_id": "76561198014472311",
      "username": "SOBS",
      "action": "disconnected",
      "x": "10276",
      "y": "9416",
      "z": "0"
    },
    {
      "timestamp": "19-12-25 21:45:04.986",
      "steam_id": "76561198044597580",
      "username": "Captain",
      "action": "attempting to join"
    },
    {
      "timestamp": "19-12-25 21:45:04.986",
      "steam_id": "76561198044597580",
      "username": "Captain",
      "action": "allowed to join"
    },
    {
      "timestamp": "19-12-25 21:45:12.627",
      "steam_id": "76561198044597580",
      "username": "Captain",
      "action": "attempting to join"
    },
    {
      "timestamp": "19-12-25 21:57:46.576",
      "steam_id": "76561198044597580",
      "username": "Captain",
      "action": "attempting to join"
    },
    {
      "timestamp": "19-12-25 21:57:46.577",
      "steam_id": "76561198044597580",
      "username": "Captain",
      "action": "allowed to join"
    },
    {
      "timestamp": "19-12-25 21:57:54.019",
      "steam_id": "76561198044597580",
      "username": "Captain",
      "action": "attempting to join"
    },
    {
      "timestamp": "19-12-25 21:58:29.373",
      "steam_id": "76561198044597580",
      "username": "Captain",
      "action": "fully connected",
      "x": "10608",
      "y": "10231",
      "z": "0"
    },
    {
      "timestamp": "19-12-25 21:58:55.304",
      "steam_id": "76561198044597580",
      "username": "Captain",
      "action": "disconnected",
      "x": "10608",
      "y": "10232",
      "z": "0"
    },
    {
      "timestamp": "19-12-25 22:17:15.077",
      "steam_id": "76561198044597580",
      "username": "Captain",
      "action": "attempting to join"
    },
    {
      "timestamp": "19-12-25 22:17:15.077",
      "steam_id": "76561198044597580",
      "username": "Captain",
      "action": "allowed to join"
    },
    {
      "timestamp": "19-12-25 22:17:22.433",
      "steam_id": "76561198044597580",
      "username": "Captain",
      "action": "attempting to join"
    },
    {
      "timestamp": "19-12-25 22:18:05.691",
      "steam_id": "76561198044597580",
      "username": "Captain",
      "action": "fully connected",
      "x": "10608",
      "y": "10232",
      "z": "0"
    },
    {
      "timestamp": "19-12-25 22:21:50.807",
      "steam_id": "76561198044597580",
      "username": "Captain",
      "action": "disconnected",
      "x": "10617",
      "y": "10059",
      "z": "0"
    },
    {
      "timestamp": "19-12-25 23:24:55.730",
      "steam_id": "76561199163725035",
      "username": "Molotov Kid",
      "action": "attempting to join"
    },
    {
      "timestamp": "19-12-25 23:24:55.731",
      "steam_id": "76561199163725035",
      "username": "Molotov Kid",
      "action": "allowed to join"
    },
    {
      "timestamp": "19-12-25 23:25:16.233",
      "steam_id": "76561199163725035",
      "username": "Molotov Kid",
      "action": "attempting to join"
    },
    {
      "timestamp": "19-12-25 23:26:50.549",
      "steam_id": "76561199163725035",
      "username": "Molotov Kid",
      "action": "fully connected",
      "x": "10098",
      "y": "8261",
      "z": "2"
    },
    {
      "timestamp": "19-12-25 23:41:20.280",
      "steam_id": "76561199163725035",
      "username": "Molotov Kid",
      "action": "disconnected",
      "x": "10081",
      "y": "8274",
      "z": "0"
    },
    {
      "timestamp": "20-12-25 00:12:35.547",
      "steam_id": "76561198031138505",
      "username": "Firestorm3050",
      "action": "attempting to join"
    },
    {
      "timestamp": "20-12-25 00:12:35.548",
      "steam_id": "76561198031138505",
      "username": "Firestorm3050",
      "action": "allowed to join"
    },
    {
      "timestamp": "20-12-25 00:38:32.171",
      "steam_id": "76561198031138505",
      "username": "Firestorm3050",
      "action": "attempting to join"
    },
    {
      "timestamp": "20-12-25 00:39:21.686",
      "steam_id": "76561198031138505",
      "username": "Firestorm3050",
      "action": "fully connected",
      "x": "10854",
      "y": "9894",
      "z": "0"
    },
    {
      "timestamp": "20-12-25 01:01:22.475",
      "steam_id": "76561199163725035",
      "username": "Molotov Kid",
      "action": "attempting to join"
    },
    {
      "timestamp": "20-12-25 01:01:22.476",
      "steam_id": "76561199163725035",
      "username": "Molotov Kid",
      "action": "allowed to join"
    },
    {
      "timestamp": "20-12-25 01:01:47.518",
      "steam_id": "76561199163725035",
      "username": "Molotov Kid",
      "action": "attempting to join"
    },
    {
      "timestamp": "20-12-25 01:02:36.876",
      "steam_id": "76561199163725035",
      "username": "Molotov Kid",
      "action": "fully connected",
      "x": "10081",
      "y": "8274",
      "z": "0"
    },
    {
      "timestamp": "20-12-25 01:50:47.211",
      "steam_id": "76561199163725035",
      "username": "Molotov Kid",
      "action": "disconnected",
      "x": "11642",
      "y": "7269",
      "z": "0"
    },
    {
      "timestamp": "20-12-25 01:52:32.624",
      "steam_id": "76561198031138505",
      "username": "Firestorm3050",
      "action": "disconnected",
      "x": "10082",
      "y": "8250",
      "z": "0"
    },
    {
      "timestamp": "20-12-25 01:56:42.109",
      "steam_id": "76561198031138505",
      "username": "Firestorm3050",
      "action": "attempting to join"
    },
    {
      "timestamp": "20-12-25 01:56:42.110",
      "steam_id": "76561198031138505",
      "username": "Firestorm3050",
      "action": "allowed to join"
    },
    {
      "timestamp": "20-12-25 01:56:54.083",
      "steam_id": "76561198031138505",
      "username": "Firestorm3050",
      "action": "attempting to join"
    },
    {
      "timestamp": "20-12-25 02:22:13.112",
      "steam_id": "76561198119296623",
      "username": "Sully",
      "action": "attempting to join"
    },
    {
      "timestamp": "20-12-25 02:22:13.112",
      "steam_id": "76561198119296623",
      "username": "Sully",
      "action": "allowed to join"
    },
    {
      "timestamp": "20-12-25 02:22:27.866",
      "steam_id": "76561198119296623",
      "username": "Sully",
      "action": "attempting to join"
    },
    {
      "timestamp": "20-12-25 02:23:04.498",
      "steam_id": "76561198119296623",
      "username": "Sully",
      "action": "fully connected",
      "x": "10875",
      "y": "10077",
      "z": "0"
    },
    {
      "timestamp": "20-12-25 02:30:51.270",
      "steam_id": "76561198031138505",
      "username": "Firestorm3050",
      "action": "fully connected",
      "x": "10082",
      "y": "8250",
      "z": "0"
    },
    {
      "timestamp": "20-12-25 02:38:55.634",
      "steam_id": "76561198119296623",
      "username": "Sully",
      "action": "disconnected",
      "x": "10874",
      "y": "10078",
      "z": "0"
    },
    {
      "timestamp": "20-12-25 03:01:24.094",
      "steam_id": "76561198031138505",
      "username": "Firestorm3050",
      "action": "disconnected",
      "x": "10112",
      "y": "8267",
      "z": "0"
    },
    {
      "timestamp": "20-12-25 06:20:29.454",
      "steam_id": "76561198065774641",
      "username": "BetoJin",
      "action": "attempting to join"
    },
    {
      "timestamp": "20-12-25 06:20:29.455",
      "steam_id": "76561198065774641",
      "username": "BetoJin",
      "action": "allowed to join"
    },
    {
      "timestamp": "20-12-25 06:20:35.970",
      "steam_id": "76561198065774641",
      "username": "BetoJin",
      "action": "attempting to join"
    },
    {
      "timestamp": "20-12-25 06:21:11.847",
      "steam_id": "76561198065774641",
      "username": "BetoJin",
      "action": "fully connected",
      "x": "10110",
      "y": "8240",
      "z": "0"
    },
    {
      "timestamp": "20-12-25 09:05:58.709",
      "steam_id": "76561198065774641",
      "username": "BetoJin",
      "action": "disconnected",
      "x": "11644",
      "y": "8108",
      "z": "0"
    }
  ],
  "perk_events": [
    {
      "timestamp": "18-12-25 20:19:22.754",
      "steam_id": "76561198044597580",
      "username": "Captain",
      "x": "10643",
      "y": "10414",
      "z": "0",
      "hours_survived": 4,
      "event_type": "login",
      "skills": {
        "Cooking": 0,
        "Fitness": 7,
        "Strength": 5,
        "Blunt": 0,
        "Axe": 0,
        "Lightfoot": 2,
        "Nimble": 2,
        "Sprinting": 0,
        "Sneak": 2,
        "Woodwork": 0,
        "Aiming": 0,
        "Reloading": 0,
        "Farming": 0,
        "Fishing": 0,
        "Trapping": 0,
        "PlantScavenging": 0,
        "Doctor": 0,
        "Electricity": 0,
        "Blacksmith": 0,
        "MetalWelding": 0,
        "Mechanics": 1,
        "Spear": 0,
        "Maintenance": 0,
        "SmallBlade": 0,
        "LongBlade": 0,
        "SmallBlunt": 0,
        "Tailoring": 0,
        "Tracking": 0,
        "Husbandry": 0,
        "FlintKnapping": 0,
        "Masonry": 0,
        "Pottery": 0,
        "Carving": 0,
        "Butchering": 0,
        "Glassmaking": 0
      }
    },
    {
      "timestamp": "18-12-25 20:36:16.346",
      "steam_id": "76561198044597580",
      "username": "Captain",
      "x": "8091",
      "y": "11346",
      "z": "0",
      "hours_survived": 11,
      "event_type": "level_up",
      "skill": "Axe",
      "level": "1"
    },
    {
      "timestamp": "18-12-25 21:02:30.015",
      "steam_id": "76561198044597580",
      "username": "Captain",
      "x": "8141",
      "y": "11253",
      "z": "0",
      "hours_survived": 21,
      "event_type": "level_up",
      "skill": "Axe",
      "level": "2"
    },
    {
      "timestamp": "18-12-25 21:53:09.060",
      "steam_id": "76561198044597580",
      "username": "Captain",
      "x": "10597",
      "y": "10214",
      "z": "0",
      "hours_survived": 5,
      "event_type": "login",
      "skills": {
        "Cooking": 0,
        "Fitness": 7,
        "Strength": 5,
        "Blunt": 0,
        "Axe": 0,
        "Lightfoot": 2,
        "Nimble": 2,
        "Sprinting": 0,
        "Sneak": 2,
        "Woodwork": 0,
        "Aiming": 0,
        "Reloading": 0,
        "Farming": 0,
        "Fishing": 0,
        "Trapping": 0,
        "PlantScavenging": 0,
        "Doctor": 0,
        "Electricity": 0,
        "Blacksmith": 0,
        "MetalWelding": 0,
        "Mechanics": 1,
        "Spear": 0,
        "Maintenance": 0,
        "SmallBlade": 0,
        "LongBlade": 0,
        "SmallBlunt": 0,
        "Tailoring": 0,
        "Tracking": 0,
        "Husbandry": 0,
        "FlintKnapping": 0,
        "Masonry": 0,
        "Pottery": 0,
        "Carving": 0,
        "Butchering": 0,
        "Glassmaking": 0
      }
    },
    {
      "timestamp": "18-12-25 23:21:54.944",
      "steam_id": "76561198044597580",
      "username": "Captain",
      "x": "10608",
      "y": "10231",
      "z": "0",
      "hours_survived": 6,
      "event_type": "login",
      "skills": {
        "Cooking": 0,
        "Fitness": 7,
        "Strength": 5,
        "Blunt": 0,
        "Axe": 0,
        "Lightfoot": 2,
        "Nimble": 2,
        "Sprinting": 0,
        "Sneak": 2,
        "Woodwork": 0,
        "Aiming": 0,
        "Reloading": 0,
        "Farming": 0,
        "Fishing": 0,
        "Trapping": 0,
        "PlantScavenging": 0,
        "Doctor": 0,
        "Electricity": 0,
        "Blacksmith": 0,
        "MetalWelding": 0,
        "Mechanics": 1,
        "Spear": 0,
        "Maintenance": 0,
        "SmallBlade": 0,
        "LongBlade": 0,
        "SmallBlunt": 0,
        "Tailoring": 0,
        "Tracking": 0,
        "Husbandry": 0,
        "FlintKnapping": 0,
        "Masonry": 0,
        "Pottery": 0,
        "Carving": 0,
        "Butchering": 0,
        "Glassmaking": 0
      }
    },
    {
      "timestamp": "18-12-25 23:25:56.544",
      "steam_id": "76561198044597580",
      "username": "Captain",
      "x": "10605",
      "y": "10539",
      "z": "0",
      "hours_survived": 7,
      "event_type": "level_up",
      "skill": "Axe",
      "level": "1"
    },
    {
      "timestamp": "18-12-25 23:48:23.602",
      "steam_id": "76561198044597580",
      "username": "Captain",
      "x": "2576",
      "y": "10928",
      "z": "0",
      "hours_survived": 16,
      "event_type": "level_up",
      "skill": "Axe",
      "level": "2"
    },
    {
      "timestamp": "18-12-25 23:58:17.976",
      "steam_id": "76561198044597580",
      "username": "Captain",
      "x": "10608",
      "y": "10231",
      "z": "0",
      "hours_survived": 6,
      "event_type": "login",
      "skills": {
        "Cooking": 0,
        "Fitness": 7,
        "Strength": 5,
        "Blunt": 0,
        "Axe": 0,
        "Lightfoot": 2,
        "Nimble": 2,
        "Sprinting": 0,
        "Sneak": 2,
        "Woodwork": 0,
        "Aiming": 0,
        "Reloading": 0,
        "Farming": 0,
        "Fishing": 0,
        "Trapping": 0,
        "PlantScavenging": 0,
        "Doctor": 0,
        "Electricity": 0,
        "Blacksmith": 0,
        "MetalWelding": 0,
        "Mechanics": 1
      }
    },
    {
      "timestamp": "19-12-25 02:36:48.022",
      "steam_id": "76561198014472311",
      "username": "SOBS",
      "x": "2650",
      "y": "10908",
      "z": "0",
      "hours_survived": 57,
      "event_type": "level_up",
      "skill": "Blunt",
      "level": "2"
    },
    {
      "timestamp": "19-12-25 03:07:17.304",
      "steam_id": "76561199163725035",
      "username": "Molotov Kid",
      "x": "10640",
      "y": "10402",
      "z": "0",
      "hours_survived": 32,
      "event_type": "login",
      "skills": {
        "Cooking": 0,
        "Fitness": 4,
        "Strength": 5,
        "Blunt": 3,
        "Axe": 1,
        "Lightfoot": 0,
        "Nimble": 0,
        "Sprinting": 0,
        "Sneak": 1,
        "Woodwork": 0,
        "Aiming": 3,
        "Reloading": 2,
        "Farming": 0,
        "Fishing": 0,
        "Trapping": 1,
        "PlantScavenging": 0,
        "Doctor": 0,
        "Electricity": 0,
        "Blacksmith": 0,
        "MetalWelding": 0,
        "Mechanics": 0,
        "Spear": 0,
        "Maintenance": 1,
        "SmallBlade": 1,
        "LongBlade": 0,
        "SmallBlunt": 0,
        "Tailoring": 0,
        "Tracking": 0,
        "Husbandry": 0,
        "FlintKnapping": 0,
        "Masonry": 0,
        "Pottery": 0,
        "Carving": 0,
        "Butchering": 1,
        "Glassmaking": 0
      }
    },
    {
      "timestamp": "19-12-25 03:12:19.591",
      "steam_id": "76561199163725035",
      "username": "Molotov Kid",
      "x": "10644",
      "y": "10414",
      "z": "0",
      "hours_survived": 33,
      "event_type": "level_up",
      "skill": "Maintenance",
      "level": "2"
    },
    {
      "timestamp": "19-12-25 04:41:28.687",
      "steam_id": "76561199163725035",
      "username": "Molotov Kid",
      "x": "10113",
      "y": "8225",
      "z": "0",
      "hours_survived": 55,
      "event_type": "login",
      "skills": {
        "Cooking": 0,
        "Fitness": 4,
        "Strength": 5,
        "Blunt": 3,
        "Axe": 1,
        "Lightfoot": 0,
        "Nimble": 0,
        "Sprinting": 0,
        "Sneak": 1,
        "Woodwork": 0,
        "Aiming": 3,
        "Reloading": 2,
        "Farming": 0,
        "Fishing": 0,
        "Trapping": 1,
        "PlantScavenging": 0,
        "Doctor": 0,
        "Electricity": 0,
        "Blacksmith": 0,
        "MetalWelding": 0,
        "Mechanics": 0,
        "Spear": 0,
        "Maintenance": 2,
        "SmallBlade": 1,
        "LongBlade": 0,
        "SmallBlunt": 0,
        "Tailoring": 0,
        "Tracking": 0,
        "Husbandry": 0,
        "FlintKnapping": 0,
        "Masonry": 0,
        "Pottery": 0,
        "Carving": 0,
        "Butchering": 1,
        "Glassmaking": 0
      }
    },
    {
      "timestamp": "19-12-25 07:08:39.332",
      "steam_id": "76561199163725035",
      "username": "Molotov Kid",
      "x": "10099",
      "y": "8258",
      "z": "0",
      "hours_survived": 63,
      "event_type": "login",
      "skills": {
        "Cooking": 0,
        "Fitness": 4,
        "Strength": 5,
        "Blunt": 3,
        "Axe": 1,
        "Lightfoot": 0,
        "Nimble": 0,
        "Sprinting": 0,
        "Sneak": 1,
        "Woodwork": 0,
        "Aiming": 3,
        "Reloading": 2,
        "Farming": 0,
        "Fishing": 0,
        "Trapping": 1,
        "PlantScavenging": 0,
        "Doctor": 0,
        "Electricity": 0,
        "Blacksmith": 0,
        "MetalWelding": 0,
        "Mechanics": 0,
        "Spear": 0,
        "Maintenance": 2,
        "SmallBlade": 1,
        "LongBlade": 0,
        "SmallBlunt": 0,
        "Tailoring": 0,
        "Tracking": 0,
        "Husbandry": 0,
        "FlintKnapping": 0,
        "Masonry": 0,
        "Pottery": 0,
        "Carving": 0,
        "Butchering": 1,
        "Glassmaking": 0
      }
    },
    {
      "timestamp": "19-12-25 07:19:00.585",
      "steam_id": "76561198065774641",
      "username": "BetoJin",
      "x": "10114",
      "y": "8241",
      "z": "0",
      "hours_survived": 54,
      "event_type": "login",
      "skills": {
        "Cooking": 0,
        "Fitness": 5,
        "Strength": 5,
        "Blunt": 2,
        "Axe": 1,
        "Lightfoot": 2,
        "Nimble": 2,
        "Sprinting": 0,
        "Sneak": 2,
        "Woodwork": 0,
        "Aiming": 0,
        "Reloading": 0,
        "Farming": 0,
        "Fishing": 0,
        "Trapping": 0,
        "PlantScavenging": 0,
        "Doctor": 0,
        "Electricity": 0,
        "Blacksmith": 0,
        "MetalWelding": 0,
        "Mechanics": 0,
        "Spear": 0,
        "Maintenance": 2,
        "SmallBlade": 0,
        "LongBlade": 0,
        "SmallBlunt": 0,
        "Tailoring": 0,
        "Tracking": 0,
        "Husbandry": 0,
        "FlintKnapping": 0,
        "Masonry": 0,
        "Pottery": 0,
        "Carving": 0,
        "Butchering": 0,
        "Glassmaking": 0
      }
    },
    {
      "timestamp": "19-12-25 07:48:56.489",
      "steam_id": "76561198065774641",
      "username": "BetoJin",
      "x": "10108",
      "y": "8239",
      "z": "0",
      "hours_survived": 58,
      "event_type": "login",
      "skills": {
        "Cooking": 0,
        "Fitness": 5,
        "Strength": 5,
        "Blunt": 2,
        "Axe": 1,
        "Lightfoot": 2,
        "Nimble": 2,
        "Sprinting": 0,
        "Sneak": 2,
        "Woodwork": 0,
        "Aiming": 0,
        "Reloading": 0,
        "Farming": 0,
        "Fishing": 0,
        "Trapping": 0,
        "PlantScavenging": 0,
        "Doctor": 0,
        "Electricity": 0,
        "Blacksmith": 0,
        "MetalWelding": 0,
        "Mechanics": 0,
        "Spear": 0,
        "Maintenance": 2,
        "SmallBlade": 0,
        "LongBlade": 0,
        "SmallBlunt": 0,
        "Tailoring": 0,
        "Tracking": 0,
        "Husbandry": 0,
        "FlintKnapping": 0,
        "Masonry": 0,
        "Pottery": 0,
        "Carving": 0,
        "Butchering": 0,
        "Glassmaking": 0
      }
    },
    {
      "timestamp": "19-12-25 07:50:35.489",
      "steam_id": "76561198065774641",
      "username": "BetoJin",
      "x": "10109",
      "y": "8240",
      "z": "0",
      "hours_survived": 59,
      "event_type": "login",
      "skills": {
        "Cooking": 0,
        "Fitness": 5,
        "Strength": 5,
        "Blunt": 2,
        "Axe": 1,
        "Lightfoot": 2,
        "Nimble": 2,
        "Sprinting": 0,
        "Sneak": 2,
        "Woodwork": 0,
        "Aiming": 0,
        "Reloading": 0,
        "Farming": 0,
        "Fishing": 0,
        "Trapping": 0,
        "PlantScavenging": 0,
        "Doctor": 0,
        "Electricity": 0,
        "Blacksmith": 0,
        "MetalWelding": 0,
        "Mechanics": 0,
        "Spear": 0,
        "Maintenance": 2,
        "SmallBlade": 0,
        "LongBlade": 0,
        "SmallBlunt": 0,
        "Tailoring": 0,
        "Tracking": 0,
        "Husbandry": 0,
        "FlintKnapping": 0,
        "Masonry": 0,
        "Pottery": 0,
        "Carving": 0,
        "Butchering": 0,
        "Glassmaking": 0
      }
    },
    {
      "timestamp": "19-12-25 15:10:28.615",
      "steam_id": "76561198014472311",
      "username": "SOBS",
      "x": "10083",
      "y": "8255",
      "z": "1",
      "hours_survived": 115,
      "event_type": "login",
      "skills": {
        "Cooking": 0,
        "Fitness": 8,
        "Strength": 5,
        "Blunt": 2,
        "Axe": 0,
        "Lightfoot": 0,
        "Nimble": 0,
        "Sprinting": 2,
        "Sneak": 0,
        "Woodwork": 0,
        "Aiming": 0,
        "Reloading": 0,
        "Farming": 0,
        "Fishing": 0,
        "Trapping": 0,
        "PlantScavenging": 0,
        "Doctor": 0,
        "Electricity": 0,
        "Blacksmith": 0,
        "MetalWelding": 0,
        "Mechanics": 1,
        "Spear": 0,
        "Maintenance": 1,
        "SmallBlade": 0,
        "LongBlade": 0,
        "SmallBlunt": 0,
        "Tailoring": 0,
        "Tracking": 0,
        "Husbandry": 0,
        "FlintKnapping": 0,
        "Masonry": 0,
        "Pottery": 0,
        "Carving": 0,
        "Butchering": 0,
        "Glassmaking": 0
      }
    },
    {
      "timestamp": "19-12-25 15:47:05.694",
      "steam_id": "76561198014472311",
      "username": "SOBS",
      "x": "10341",
      "y": "9314",
      "z": "0",
      "hours_survived": 129,
      "event_type": "level_up",
      "skill": "Sprinting",
      "level": "3"
    },
    {
      "timestamp": "19-12-25 21:58:30.704",
      "steam_id": "76561198044597580",
      "username": "Captain",
      "x": "10608",
      "y": "10231",
      "z": "0",
      "hours_survived": 6,
      "event_type": "login",
      "skills": {
        "Cooking": 0,
        "Fitness": 7,
        "Strength": 5,
        "Blunt": 0,
        "Axe": 0,
        "Lightfoot": 2,
        "Nimble": 2,
        "Sprinting": 0,
        "Sneak": 2,
        "Woodwork": 0,
        "Aiming": 0,
        "Reloading": 0,
        "Farming": 0,
        "Fishing": 0,
        "Trapping": 0,
        "PlantScavenging": 0,
        "Doctor": 0,
        "Electricity": 0,
        "Blacksmith": 0,
        "MetalWelding": 0,
        "Mechanics": 1,
        "Spear": 0,
        "Maintenance": 0,
        "SmallBlade": 0,
        "LongBlade": 0,
        "SmallBlunt": 0,
        "Tailoring": 0,
        "Tracking": 0,
        "Husbandry": 0,
        "FlintKnapping": 0,
        "Masonry": 0,
        "Pottery": 0,
        "Carving": 0,
        "Butchering": 0,
        "Glassmaking": 0
      }
    },
    {
      "timestamp": "19-12-25 22:18:06.409",
      "steam_id": "76561198044597580",
      "username": "Captain",
      "x": "10608",
      "y": "10232",
      "z": "0",
      "hours_survived": 6,
      "event_type": "login",
      "skills": {
        "Cooking": 0,
        "Fitness": 7,
        "Strength": 5,
        "Blunt": 0,
        "Axe": 0,
        "Lightfoot": 2,
        "Nimble": 2,
        "Sprinting": 0,
        "Sneak": 2,
        "Woodwork": 0,
        "Aiming": 0,
        "Reloading": 0,
        "Farming": 0,
        "Fishing": 0,
        "Trapping": 0,
        "PlantScavenging": 0,
        "Doctor": 0,
        "Electricity": 0,
        "Blacksmith": 0,
        "MetalWelding": 0,
        "Mechanics": 1,
        "Spear": 0,
        "Maintenance": 0,
        "SmallBlade": 0,
        "LongBlade": 0,
        "SmallBlunt": 0,
        "Tailoring": 0,
        "Tracking": 0,
        "Husbandry": 0,
        "FlintKnapping": 0,
        "Masonry": 0,
        "Pottery": 0,
        "Carving": 0,
        "Butchering": 0,
        "Glassmaking": 0
      }
    },
    {
      "timestamp": "19-12-25 23:26:57.960",
      "steam_id": "76561199163725035",
      "username": "Molotov Kid",
      "x": "10098",
      "y": "8261",
      "z": "2",
      "hours_survived": 65,
      "event_type": "login",
      "skills": {
        "Cooking": 0,
        "Fitness": 4,
        "Strength": 5,
        "Blunt": 3,
        "Axe": 1,
        "Lightfoot": 0,
        "Nimble": 0,
        "Sprinting": 0,
        "Sneak": 1,
        "Woodwork": 0,
        "Aiming": 3,
        "Reloading": 2,
        "Farming": 0,
        "Fishing": 0,
        "Trapping": 1,
        "PlantScavenging": 0,
        "Doctor": 0,
        "Electricity": 0,
        "Blacksmith": 0,
        "MetalWelding": 0,
        "Mechanics": 0,
        "Spear": 0,
        "Maintenance": 2,
        "SmallBlade": 1,
        "LongBlade": 0,
        "SmallBlunt": 0,
        "Tailoring": 0,
        "Tracking": 0,
        "Husbandry": 0,
        "FlintKnapping": 0,
        "Masonry": 0,
        "Pottery": 0,
        "Carving": 0,
        "Butchering": 1,
        "Glassmaking": 0
      }
    },
    {
      "timestamp": "20-12-25 00:39:22.247",
      "steam_id": "76561198031138505",
      "username": "Firestorm3050",
      "x": "10854",
      "y": "9894",
      "z": "0",
      "hours_survived": 0,
      "event_type": "login",
      "skills": {
        "Cooking": 0,
        "Fitness": 10,
        "Strength": 9,
        "Blunt": 0,
        "Axe": 0,
        "Lightfoot": 0,
        "Nimble": 0,
        "Sprinting": 2,
        "Sneak": 0,
        "Woodwork": 0,
        "Aiming": 0,
        "Reloading": 0,
        "Farming": 0,
        "Fishing": 0,
        "Trapping": 0,
        "PlantScavenging": 0,
        "Doctor": 0,
        "Electricity": 0,
        "Blacksmith": 0,
        "MetalWelding": 0,
        "Mechanics": 0,
        "Spear": 0,
        "Maintenance": 0,
        "SmallBlade": 0,
        "LongBlade": 0,
        "SmallBlunt": 0,
        "Tailoring": 0,
        "Tracking": 0,
        "Husbandry": 0,
        "FlintKnapping": 0,
        "Masonry": 0,
        "Pottery": 0,
        "Carving": 0,
        "Butchering": 0,
        "Glassmaking": 0
      }
    },
    {
      "timestamp": "20-12-25 01:02:40.246",
      "steam_id": "76561199163725035",
      "username": "Molotov Kid",
      "x": "10081",
      "y": "8274",
      "z": "0",
      "hours_survived": 71,
      "event_type": "login",
      "skills": {
        "Cooking": 0,
        "Fitness": 4,
        "Strength": 5,
        "Blunt": 3,
        "Axe": 1,
        "Lightfoot": 0,
        "Nimble": 0,
        "Sprinting": 0,
        "Sneak": 1,
        "Woodwork": 0,
        "Aiming": 3,
        "Reloading": 2,
        "Farming": 0,
        "Fishing": 0,
        "Trapping": 1,
        "PlantScavenging": 0,
        "Doctor": 0,
        "Electricity": 0,
        "Blacksmith": 0,
        "MetalWelding": 0,
        "Mechanics": 0,
        "Spear": 0,
        "Maintenance": 2,
        "SmallBlade": 1,
        "LongBlade": 0,
        "SmallBlunt": 0,
        "Tailoring": 0,
        "Tracking": 0,
        "Husbandry": 0,
        "FlintKnapping": 0,
        "Masonry": 0,
        "Pottery": 0,
        "Carving": 0,
        "Butchering": 1,
        "Glassmaking": 0
      }
    },
    {
      "timestamp": "20-12-25 01:06:25.878",
      "steam_id": "76561199163725035",
      "username": "Molotov Kid",
      "x": "10079",
      "y": "8252",
      "z": "0",
      "hours_survived": 72,
      "event_type": "level_up",
      "skill": "Sprinting",
      "level": "1"
    },
    {
      "timestamp": "20-12-25 01:27:56.319",
      "steam_id": "76561198031138505",
      "username": "Firestorm3050",
      "x": "10112",
      "y": "8280",
      "z": "0",
      "hours_survived": 19,
      "event_type": "level_up",
      "skill": "Cooking",
      "level": "1"
    },
    {
      "timestamp": "20-12-25 01:28:36.820",
      "steam_id": "76561198031138505",
      "username": "Firestorm3050",
      "x": "10112",
      "y": "8280",
      "z": "0",
      "hours_survived": 19,
      "event_type": "level_up",
      "skill": "Cooking",
      "level": "2"
    },
    {
      "timestamp": "20-12-25 02:23:06.825",
      "steam_id": "76561198119296623",
      "username": "Sully",
      "x": "10875",
      "y": "10077",
      "z": "0",
      "hours_survived": 69,
      "event_type": "login",
      "skills": {
        "Cooking": 0,
        "Fitness": 5,
        "Strength": 9,
        "Blunt": 3,
        "Axe": 0,
        "Lightfoot": 2,
        "Nimble": 2,
        "Sprinting": 1,
        "Sneak": 2,
        "Woodwork": 0,
        "Aiming": 0,
        "Reloading": 0,
        "Farming": 0,
        "Fishing": 0,
        "Trapping": 0,
        "PlantScavenging": 0,
        "Doctor": 0,
        "Electricity": 0,
        "Blacksmith": 0,
        "MetalWelding": 0,
        "Mechanics": 0,
        "Spear": 0,
        "Maintenance": 2,
        "SmallBlade": 0,
        "LongBlade": 0,
        "SmallBlunt": 1,
        "Tailoring": 0,
        "Tracking": 0,
        "Husbandry": 0,
        "FlintKnapping": 0,
        "Masonry": 0,
        "Pottery": 0,
        "Carving": 0,
        "Butchering": 0,
        "Glassmaking": 0
      }
    },
    {
      "timestamp": "20-12-25 02:30:51.708",
      "steam_id": "76561198031138505",
      "username": "Firestorm3050",
      "x": "10082",
      "y": "8250",
      "z": "0",
      "hours_survived": 29,
      "event_type": "login",
      "skills": {
        "Cooking": 2,
        "Fitness": 10,
        "Strength": 9,
        "Blunt": 0,
        "Axe": 0,
        "Lightfoot": 0,
        "Nimble": 0,
        "Sprinting": 2,
        "Sneak": 0,
        "Woodwork": 0,
        "Aiming": 0,
        "Reloading": 0,
        "Farming": 0,
        "Fishing": 0,
        "Trapping": 0,
        "PlantScavenging": 0,
        "Doctor": 0,
        "Electricity": 0,
        "Blacksmith": 0,
        "MetalWelding": 0,
        "Mechanics": 0,
        "Spear": 0,
        "Maintenance": 0,
        "SmallBlade": 0,
        "LongBlade": 0,
        "SmallBlunt": 0,
        "Tailoring": 0,
        "Tracking": 0,
        "Husbandry": 0,
        "FlintKnapping": 0,
        "Masonry": 0,
        "Pottery": 0,
        "Carving": 0,
        "Butchering": 0,
        "Glassmaking": 0
      }
    },
    {
      "timestamp": "20-12-25 06:21:12.383",
      "steam_id": "76561198065774641",
      "username": "BetoJin",
      "x": "10110",
      "y": "8240",
      "z": "0",
      "hours_survived": 59,
      "event_type": "login",
      "skills": {
        "Cooking": 0,
        "Fitness": 5,
        "Strength": 5,
        "Blunt": 2,
        "Axe": 1,
        "Lightfoot": 2,
        "Nimble": 2,
        "Sprinting": 0,
        "Sneak": 2,
        "Woodwork": 0,
        "Aiming": 0,
        "Reloading": 0,
        "Farming": 0,
        "Fishing": 0,
        "Trapping": 0,
        "PlantScavenging": 0,
        "Doctor": 0,
        "Electricity": 0,
        "Blacksmith": 0,
        "MetalWelding": 0,
        "Mechanics": 0,
        "Spear": 0,
        "Maintenance": 2,
        "SmallBlade": 0,
        "LongBlade": 0,
        "SmallBlunt": 0,
        "Tailoring": 0,
        "Tracking": 0,
        "Husbandry": 0,
        "FlintKnapping": 0,
        "Masonry": 0,
        "Pottery": 0,
        "Carving": 0,
        "Butchering": 0,
        "Glassmaking": 0
      }
    },
    {
      "timestamp": "20-12-25 07:30:10.445",
      "steam_id": "76561198065774641",
      "username": "BetoJin",
      "x": "10068",
      "y": "8241",
      "z": "0",
      "hours_survived": 87,
      "event_type": "level_up",
      "skill": "Sprinting",
      "level": "1"
    }
  ],
  "chat_messages": [
    {
      "timestamp": "20-12-25 01:18:49.999",
      "chat_type": "Local",
      "author": "Firestorm3050",
      "text": "i have a frying pan so i can cook stir frys to undo the unhappiness from looting corpses"
    },
    {
      "timestamp": "20-12-25 01:18:50.000",
      "chat_type": "Local",
      "author": "Firestorm3050",
      "text": "i have a frying pan so i can cook stir frys to undo the unhappiness from looting corpses"
    },
    {
      "timestamp": "20-12-25 01:19:51.596",
      "chat_type": "Local",
      "author": "Firestorm3050",
      "text": "also, you cant craft most things without light now"
    },
    {
      "timestamp": "20-12-25 01:19:51.596",
      "chat_type": "Local",
      "author": "Firestorm3050",
      "text": "also, you cant craft most things without light now"
    },
    {
      "timestamp": "20-12-25 01:20:10.064",
      "chat_type": "Local",
      "author": "Firestorm3050",
      "text": "and a lot need solid surfaces like tables"
    },
    {
      "timestamp": "20-12-25 01:20:10.064",
      "chat_type": "Local",
      "author": "Firestorm3050",
      "text": "and a lot need solid surfaces like tables"
    },
    {
      "timestamp": "20-12-25 01:20:35.159",
      "chat_type": "Local",
      "author": "Firestorm3050",
      "text": "but most lootable items are craftable now if you know how"
    },
    {
      "timestamp": "20-12-25 01:20:35.159",
      "chat_type": "Local",
      "author": "Firestorm3050",
      "text": "but most lootable items are craftable now if you know how"
    },
    {
      "timestamp": "20-12-25 01:20:56.741",
      "chat_type": "Local",
      "author": "Firestorm3050",
      "text": "even swords, machetes, and medieval knight armor"
    },
    {
      "timestamp": "20-12-25 01:20:56.741",
      "chat_type": "Local",
      "author": "Firestorm3050",
      "text": "even swords, machetes, and medieval knight armor"
    },
    {
      "timestamp": "20-12-25 01:22:40.844",
      "chat_type": "Local",
      "author": "Firestorm3050",
      "text": "also, be careful not to use heavy thread. its rare and needed to make armor"
    },
    {
      "timestamp": "20-12-25 01:22:40.845",
      "chat_type": "Local",
      "author": "Firestorm3050",
      "text": "also, be careful not to use heavy thread. its rare and needed to make armor"
    },
    {
      "timestamp": "20-12-25 01:23:23.931",
      "chat_type": "Local",
      "author": "Firestorm3050",
      "text": "its made from animal sinew, or disassembling body armor"
    },
    {
      "timestamp": "20-12-25 01:23:23.931",
      "chat_type": "Local",
      "author": "Firestorm3050",
      "text": "its made from animal sinew, or disassembling body armor"
    },
    {
      "timestamp": "20-12-25 01:24:32.475",
      "chat_type": "Local",
      "author": "Firestorm3050",
      "text": "these braziers normally light a fire in them for light and heat, but the recent update they stopped working"
    },
    {
      "timestamp": "20-12-25 01:24:32.475",
      "chat_type": "Local",
      "author": "Firestorm3050",
      "text": "these braziers normally light a fire in them for light and heat, but the recent update they stopped working"
    },
    {
      "timestamp": "20-12-25 01:30:29.985",
      "chat_type": "Local",
      "author": "Firestorm3050",
      "text": "there is cooked food where i am at if you need it"
    },
    {
      "timestamp": "20-12-25 01:30:29.985",
      "chat_type": "Local",
      "author": "Firestorm3050",
      "text": "there is cooked food where i am at if you need it"
    },
    {
      "timestamp": "20-12-25 01:31:10.250",
      "chat_type": "Local",
      "author": "Firestorm3050",
      "text": "ran out of fuel for the stir fry tho"
    },
    {
      "timestamp": "20-12-25 01:31:10.251",
      "chat_type": "Local",
      "author": "Firestorm3050",
      "text": "ran out of fuel for the stir fry tho"
    },
    {
      "timestamp": "20-12-25 01:33:20.599",
      "chat_type": "Local",
      "author": "Firestorm3050",
      "text": "also, vhs/life and living only give xp up to lv 3 now"
    },
    {
      "timestamp": "20-12-25 01:33:20.599",
      "chat_type": "Local",
      "author": "Firestorm3050",
      "text": "also, vhs/life and living only give xp up to lv 3 now"
    },
    {
      "timestamp": "20-12-25 01:33:24.169",
      "chat_type": "Local",
      "author": "Molotov Kid",
      "text": "oh wait i forgot to unload my cooler"
    },
    {
      "timestamp": "20-12-25 01:33:24.169",
      "chat_type": "Local",
      "author": "Molotov Kid",
      "text": "oh wait i forgot to unload my cooler"
    },
    {
      "timestamp": "20-12-25 01:34:20.010",
      "chat_type": "Local",
      "author": "Firestorm3050",
      "text": "im reading wilderness survival magazine atm"
    },
    {
      "timestamp": "20-12-25 01:34:20.010",
      "chat_type": "Local",
      "author": "Firestorm3050",
      "text": "im reading wilderness survival magazine atm"
    },
    {
      "timestamp": "20-12-25 01:35:06.934",
      "chat_type": "Local",
      "author": "Firestorm3050",
      "text": "dog hemp bane turns into twine btw, its very valuable for a lot of things"
    },
    {
      "timestamp": "20-12-25 01:35:06.935",
      "chat_type": "Local",
      "author": "Firestorm3050",
      "text": "dog hemp bane turns into twine btw, its very valuable for a lot of things"
    },
    {
      "timestamp": "20-12-25 01:35:22.540",
      "chat_type": "Local",
      "author": "Firestorm3050",
      "text": "find it foraging"
    },
    {
      "timestamp": "20-12-25 01:35:22.541",
      "chat_type": "Local",
      "author": "Firestorm3050",
      "text": "find it foraging"
    },
    {
      "timestamp": "20-12-25 01:35:37.138",
      "chat_type": "Local",
      "author": "Firestorm3050",
      "text": "clay is valuable too, but its mostly for making our crafting stations that we already have here"
    },
    {
      "timestamp": "20-12-25 01:35:37.138",
      "chat_type": "Local",
      "author": "Firestorm3050",
      "text": "clay is valuable too, but its mostly for making our crafting stations that we already have here"
    },
    {
      "timestamp": "20-12-25 01:38:01.573",
      "chat_type": "Local",
      "author": "Firestorm3050",
      "text": "hah reading..."
    },
    {
      "timestamp": "20-12-25 01:38:01.573",
      "chat_type": "Local",
      "author": "Firestorm3050",
      "text": "hah reading..."
    },
    {
      "timestamp": "20-12-25 01:38:08.633",
      "chat_type": "Local",
      "author": "Firestorm3050",
      "text": "i took slow reader..."
    },
    {
      "timestamp": "20-12-25 01:38:08.633",
      "chat_type": "Local",
      "author": "Firestorm3050",
      "text": "i took slow reader..."
    },
    {
      "timestamp": "20-12-25 01:39:53.661",
      "chat_type": "Local",
      "author": "Firestorm3050",
      "text": "i am tempted to turn on a podcast to finish this lol"
    },
    {
      "timestamp": "20-12-25 01:39:53.662",
      "chat_type": "Local",
      "author": "Firestorm3050",
      "text": "i am tempted to turn on a podcast to finish this lol"
    },
    {
      "timestamp": "20-12-25 01:41:23.943",
      "chat_type": "Local",
      "author": "Firestorm3050",
      "text": "you also need light to read"
    },
    {
      "timestamp": "20-12-25 01:41:23.944",
      "chat_type": "Local",
      "author": "Firestorm3050",
      "text": "you also need light to read"
    },
    {
      "timestamp": "20-12-25 01:45:42.325",
      "chat_type": "General",
      "author": "Firestorm3050",
      "text": "75% done reading"
    },
    {
      "timestamp": "20-12-25 01:45:42.325",
      "chat_type": "General",
      "author": "Firestorm3050",
      "text": "75% done reading"
    },
    {
      "timestamp": "20-12-25 01:46:09.214",
      "chat_type": "General",
      "author": "Firestorm3050",
      "text": "its wilderness survival so ill know the poison berries or mushrooms"
    },
    {
      "timestamp": "20-12-25 01:46:09.214",
      "chat_type": "General",
      "author": "Firestorm3050",
      "text": "its wilderness survival so ill know the poison berries or mushrooms"
    },
    {
      "timestamp": "20-12-25 01:46:35.262",
      "chat_type": "General",
      "author": "Firestorm3050",
      "text": "long sticks, long branches, and dog hemp is super valuable btw"
    },
    {
      "timestamp": "20-12-25 01:46:35.262",
      "chat_type": "General",
      "author": "Firestorm3050",
      "text": "long sticks, long branches, and dog hemp is super valuable btw"
    },
    {
      "timestamp": "20-12-25 01:46:42.362",
      "chat_type": "General",
      "author": "Firestorm3050",
      "text": "bring those back if you forage them"
    },
    {
      "timestamp": "20-12-25 01:46:42.362",
      "chat_type": "General",
      "author": "Firestorm3050",
      "text": "bring those back if you forage them"
    },
    {
      "timestamp": "20-12-25 01:47:43.148",
      "chat_type": "General",
      "author": "Firestorm3050",
      "text": "flat stones make axes and other useful tools, large stones are a pain, but they make the workstations (dont need at this base)"
    },
    {
      "timestamp": "20-12-25 01:47:43.148",
      "chat_type": "General",
      "author": "Firestorm3050",
      "text": "flat stones make axes and other useful tools, large stones are a pain, but they make the workstations (dont need at this base)"
    }
  ],
  "timestamp": "2025-12-20T15:00:01.450511"
}