{
  "user_events": [
    {
      "timestamp": "29-12-25 22:41:08.612",
      "steam_id": "76561198065774641",
      "username": "admin",
      "action": "attempting to join"
    },
    {
      "timestamp": "29-12-25 22:41:08.613",
      "steam_id": "76561198065774641",
      "username": "admin",
      "action": "allowed to join"
    },
    {
      "timestamp": "29-12-25 22:41:22.536",
      "steam_id": "76561198065774641",
      "username": "admin",
      "action": "attempting to join"
    },
    {
      "timestamp": "29-12-25 22:41:37.951",
      "steam_id": "76561198065774641",
      "username": "admin",
      "action": "fully connected",
      "x": "11783",
      "y": "3606",
      "z": "0"
    },
    {
      "timestamp": "29-12-25 22:42:55.456",
      "steam_id": "76561199511597958",
      "username": "RottenPotato",
      "action": "attempting to join"
    },
    {
      "timestamp": "29-12-25 22:42:55.457",
      "steam_id": "76561199511597958",
      "username": "RottenPotato",
      "action": "allowed to join"
    },
    {
      "timestamp": "29-12-25 22:43:19.059",
      "steam_id": "76561199511597958",
      "username": "RottenPotato",
      "action": "attempting to join"
    },
    {
      "timestamp": "29-12-25 22:43:45.421",
      "steam_id": "76561199511597958",
      "username": "RottenPotato",
      "action": "fully connected",
      "x": "12023",
      "y": "2593",
      "z": "0"
    },
    {
      "timestamp": "29-12-25 22:55:23.155",
      "steam_id": "76561199511597958",
      "username": "RottenPotato",
      "action": "disconnected",
      "x": "12019",
      "y": "2594",
      "z": "0"
    }
  ],
  "perk_events": [
    {
      "timestamp": "29-12-25 03:24:04.498",
      "steam_id": "76561198060886931",
      "username": "Zero",
      "x": "8615",
      "y": "8823",
      "z": "0",
      "hours_survived": 558,
      "event_type": "login",
      "skills": {
        "Cooking": 3,
        "Fitness": 7,
        "Strength": 5,
        "Blunt": 1,
        "Axe": 0,
        "Lightfoot": 0,
        "Nimble": 0,
        "Sprinting": 3,
        "Sneak": 0,
        "Woodwork": 6,
        "Aiming": 0,
        "Reloading": 1,
        "Farming": 0,
        "Fishing": 0,
        "Trapping": 0,
        "PlantScavenging": 6,
        "Doctor": 1,
        "Electricity": 0,
        "Blacksmith": 0,
        "MetalWelding": 0,
        "Mechanics": 0,
        "Spear": 0,
        "Maintenance": 5,
        "SmallBlade": 0,
        "LongBlade": 0,
        "SmallBlunt": 1,
        "Tailoring": 2,
        "Tracking": 0,
        "Husbandry": 2,
        "FlintKnapping": 2,
        "Masonry": 4,
        "Pottery": 0,
        "Carving": 7,
        "Butchering": 3,
        "Glassmaking": 0
      }
    },
    {
      "timestamp": "29-12-25 03:45:20.670",
      "steam_id": "76561198060886931",
      "username": "Zero",
      "x": "8621",
      "y": "8828",
      "z": "0",
      "hours_survived": 566,
      "event_type": "level_up",
      "skill": "Mechanics",
      "level": "1"
    },
    {
      "timestamp": "29-12-25 04:19:09.224",
      "steam_id": "76561198060886931",
      "username": "Zero",
      "x": "8616",
      "y": "8823",
      "z": "0",
      "hours_survived": 579,
      "event_type": "login",
      "skills": {
        "Cooking": 3,
        "Fitness": 7,
        "Strength": 5,
        "Blunt": 1,
        "Axe": 0,
        "Lightfoot": 0,
        "Nimble": 0,
        "Sprinting": 3,
        "Sneak": 0,
        "Woodwork": 6,
        "Aiming": 0,
        "Reloading": 1,
        "Farming": 0,
        "Fishing": 0,
        "Trapping": 0,
        "PlantScavenging": 6,
        "Doctor": 1,
        "Electricity": 0,
        "Blacksmith": 0,
        "MetalWelding": 0,
        "Mechanics": 1,
        "Spear": 0,
        "Maintenance": 5,
        "SmallBlade": 0,
        "LongBlade": 0,
        "SmallBlunt": 1,
        "Tailoring": 2,
        "Tracking": 0,
        "Husbandry": 2,
        "FlintKnapping": 2,
        "Masonry": 4,
        "Pottery": 0,
        "Carving": 7,
        "Butchering": 3,
        "Glassmaking": 0
      }
    },
    {
      "timestamp": "29-12-25 04:38:38.087",
      "steam_id": "76561198119296623",
      "username": "Sully",
      "x": "13956",
      "y": "5920",
      "z": "0",
      "hours_survived": 1073,
      "event_type": "level_up",
      "skill": "Aiming",
      "level": "4"
    },
    {
      "timestamp": "29-12-25 04:57:41.875",
      "steam_id": "76561198119296623",
      "username": "Sully",
      "x": "13889",
      "y": "5928",
      "z": "0",
      "hours_survived": 1081,
      "event_type": "level_up",
      "skill": "Nimble",
      "level": "4"
    },
    {
      "timestamp": "29-12-25 05:10:04.707",
      "steam_id": "76561198119296623",
      "username": "Sully",
      "x": "13863",
      "y": "5841",
      "z": "0",
      "hours_survived": 1086,
      "event_type": "level_up",
      "skill": "Reloading",
      "level": "5"
    },
    {
      "timestamp": "29-12-25 05:26:15.074",
      "steam_id": "76561199511597958",
      "username": "RottenPotato",
      "x": "12045",
      "y": "2601",
      "z": "0",
      "hours_survived": 160,
      "event_type": "login",
      "skills": {
        "Cooking": 0,
        "Fitness": 10,
        "Strength": 10,
        "Blunt": 0,
        "Axe": 4,
        "Lightfoot": 0,
        "Nimble": 0,
        "Sprinting": 2,
        "Sneak": 0,
        "Woodwork": 3,
        "Aiming": 0,
        "Reloading": 1,
        "Farming": 0,
        "Fishing": 0,
        "Trapping": 0,
        "PlantScavenging": 0,
        "Doctor": 0,
        "Electricity": 2,
        "Blacksmith": 0,
        "MetalWelding": 0,
        "Mechanics": 0,
        "Spear": 0,
        "Maintenance": 3,
        "SmallBlade": 0,
        "LongBlade": 0,
        "SmallBlunt": 0,
        "Tailoring": 0,
        "Tracking": 0,
        "Husbandry": 0,
        "FlintKnapping": 0,
        "Masonry": 0,
        "Pottery": 0,
        "Carving": 0,
        "Butchering": 0,
        "Glassmaking": 0
      }
    },
    {
      "timestamp": "29-12-25 05:49:46.537",
      "steam_id": "76561199511597958",
      "username": "RottenPotato",
      "x": "12098",
      "y": "2605",
      "z": "0",
      "hours_survived": 169,
      "event_type": "level_up",
      "skill": "Masonry",
      "level": "1"
    },
    {
      "timestamp": "29-12-25 07:45:47.600",
      "steam_id": "76561199511597958",
      "username": "RottenPotato",
      "x": "12012",
      "y": "2588",
      "z": "0",
      "hours_survived": 216,
      "event_type": "level_up",
      "skill": "Woodwork",
      "level": "4"
    },
    {
      "timestamp": "29-12-25 08:27:40.652",
      "steam_id": "76561199511597958",
      "username": "RottenPotato",
      "x": "12013",
      "y": "2591",
      "z": "0",
      "hours_survived": 232,
      "event_type": "level_up",
      "skill": "Masonry",
      "level": "2"
    },
    {
      "timestamp": "29-12-25 10:19:16.707",
      "steam_id": "76561199511597958",
      "username": "RottenPotato",
      "x": "12202",
      "y": "1614",
      "z": "0",
      "hours_survived": 277,
      "event_type": "level_up",
      "skill": "Maintenance",
      "level": "4"
    },
    {
      "timestamp": "29-12-25 10:57:57.554",
      "steam_id": "76561199511597958",
      "username": "RottenPotato",
      "x": "12012",
      "y": "2589",
      "z": "0",
      "hours_survived": 292,
      "event_type": "level_up",
      "skill": "Masonry",
      "level": "3"
    },
    {
      "timestamp": "29-12-25 14:52:02.961",
      "steam_id": "76561198031138505",
      "username": "Firestorm3050",
      "x": "10659",
      "y": "9567",
      "z": "0",
      "hours_survived": 1381,
      "event_type": "login",
      "skills": {
        "Cooking": 6,
        "Fitness": 10,
        "Strength": 9,
        "Blunt": 3,
        "Axe": 0,
        "Lightfoot": 0,
        "Nimble": 1,
        "Sprinting": 5,
        "Sneak": 0,
        "Woodwork": 7,
        "Aiming": 0,
        "Reloading": 2,
        "Farming": 4,
        "Fishing": 4,
        "Trapping": 2,
        "PlantScavenging": 6,
        "Doctor": 0,
        "Electricity": 3,
        "Blacksmith": 0,
        "MetalWelding": 0,
        "Mechanics": 2,
        "Spear": 1,
        "Maintenance": 6,
        "SmallBlade": 0,
        "LongBlade": 1,
        "SmallBlunt": 4,
        "Tailoring": 2,
        "Tracking": 0,
        "Husbandry": 2,
        "FlintKnapping": 3,
        "Masonry": 8,
        "Pottery": 0,
        "Carving": 7,
        "Butchering": 2,
        "Glassmaking": 0
      }
    },
    {
      "timestamp": "29-12-25 15:45:38.359",
      "steam_id": "76561198031138505",
      "username": "Firestorm3050",
      "x": "10659",
      "y": "9571",
      "z": "0",
      "hours_survived": 1390,
      "event_type": "login",
      "skills": {
        "Cooking": 6,
        "Fitness": 10,
        "Strength": 9,
        "Blunt": 3,
        "Axe": 0,
        "Lightfoot": 0,
        "Nimble": 1,
        "Sprinting": 5,
        "Sneak": 0,
        "Woodwork": 7,
        "Aiming": 0,
        "Reloading": 2,
        "Farming": 4,
        "Fishing": 4,
        "Trapping": 2,
        "PlantScavenging": 6,
        "Doctor": 0,
        "Electricity": 3,
        "Blacksmith": 0,
        "MetalWelding": 0,
        "Mechanics": 2,
        "Spear": 1,
        "Maintenance": 6,
        "SmallBlade": 0,
        "LongBlade": 1,
        "SmallBlunt": 4,
        "Tailoring": 2,
        "Tracking": 0,
        "Husbandry": 2,
        "FlintKnapping": 3,
        "Masonry": 8,
        "Pottery": 0,
        "Carving": 7,
        "Butchering": 2,
        "Glassmaking": 0
      }
    },
    {
      "timestamp": "29-12-25 16:16:55.381",
      "steam_id": "76561198031138505",
      "username": "Firestorm3050",
      "x": "10662",
      "y": "9565",
      "z": "1",
      "hours_survived": 1403,
      "event_type": "level_up",
      "skill": "Tailoring",
      "level": "3"
    },
    {
      "timestamp": "29-12-25 16:33:31.678",
      "steam_id": "76561198031138505",
      "username": "Firestorm3050",
      "x": "10665",
      "y": "9560",
      "z": "0",
      "hours_survived": 1409,
      "event_type": "level_up",
      "skill": "Husbandry",
      "level": "3"
    },
    {
      "timestamp": "29-12-25 17:37:47.641",
      "steam_id": "76561198031138505",
      "username": "Firestorm3050",
      "x": "11018",
      "y": "10263",
      "z": "0",
      "hours_survived": 1435,
      "event_type": "level_up",
      "skill": "Fishing",
      "level": "5"
    },
    {
      "timestamp": "29-12-25 18:06:57.858",
      "steam_id": "76561198031138505",
      "username": "Firestorm3050",
      "x": "10659",
      "y": "9566",
      "z": "0",
      "hours_survived": 1447,
      "event_type": "level_up",
      "skill": "Butchering",
      "level": "3"
    },
    {
      "timestamp": "29-12-25 18:20:27.654",
      "steam_id": "76561198031138505",
      "username": "Firestorm3050",
      "x": "10659",
      "y": "9566",
      "z": "0",
      "hours_survived": 1452,
      "event_type": "level_up",
      "skill": "Reloading",
      "level": "3"
    },
    {
      "timestamp": "29-12-25 18:30:24.058",
      "steam_id": "76561198031138505",
      "username": "Firestorm3050",
      "x": "10660",
      "y": "9566",
      "z": "0",
      "hours_survived": 1456,
      "event_type": "level_up",
      "skill": "Reloading",
      "level": "4"
    },
    {
      "timestamp": "29-12-25 18:54:21.447",
      "steam_id": "76561198044597580",
      "username": "CaptainLobo",
      "x": "6704",
      "y": "6759",
      "z": "0",
      "hours_survived": 627,
      "event_type": "login",
      "skills": {
        "Cooking": 3,
        "Fitness": 7,
        "Strength": 7,
        "Blunt": 2,
        "Axe": 3,
        "Lightfoot": 2,
        "Nimble": 3,
        "Sprinting": 3,
        "Sneak": 2,
        "Woodwork": 4,
        "Aiming": 4,
        "Reloading": 4,
        "Farming": 0,
        "Fishing": 3,
        "Trapping": 3,
        "PlantScavenging": 2,
        "Doctor": 0,
        "Electricity": 0,
        "Blacksmith": 0,
        "MetalWelding": 0,
        "Mechanics": 3,
        "Spear": 0,
        "Maintenance": 2,
        "SmallBlade": 0,
        "LongBlade": 0,
        "SmallBlunt": 0,
        "Tailoring": 2,
        "Tracking": 0,
        "Husbandry": 0,
        "FlintKnapping": 0,
        "Masonry": 0,
        "Pottery": 0,
        "Carving": 0,
        "Butchering": 0,
        "Glassmaking": 0
      }
    },
    {
      "timestamp": "29-12-25 21:13:40.732",
      "steam_id": "76561198065774641",
      "username": "BetoJin",
      "x": "12021",
      "y": "2596",
      "z": "0",
      "hours_survived": 582,
      "event_type": "login",
      "skills": {
        "Cooking": 1,
        "Fitness": 10,
        "Strength": 10,
        "Blunt": 0,
        "Axe": 6,
        "Lightfoot": 0,
        "Nimble": 1,
        "Sprinting": 3,
        "Sneak": 0,
        "Woodwork": 7,
        "Aiming": 0,
        "Reloading": 0,
        "Farming": 0,
        "Fishing": 0,
        "Trapping": 1,
        "PlantScavenging": 0,
        "Doctor": 1,
        "Electricity": 2,
        "Blacksmith": 0,
        "MetalWelding": 0,
        "Mechanics": 1,
        "Spear": 0,
        "Maintenance": 4,
        "SmallBlade": 0,
        "LongBlade": 0,
        "SmallBlunt": 0,
        "Tailoring": 0,
        "Tracking": 0,
        "Husbandry": 0,
        "FlintKnapping": 0,
        "Masonry": 0,
        "Pottery": 0,
        "Carving": 0,
        "Butchering": 0,
        "Glassmaking": 0
      }
    },
    {
      "timestamp": "29-12-25 21:19:03.124",
      "steam_id": "76561198065774641",
      "username": "BetoJin",
      "x": "12495",
      "y": "3455",
      "z": "0",
      "hours_survived": 584,
      "event_type": "level_up",
      "skill": "MetalWelding",
      "level": "1"
    },
    {
      "timestamp": "29-12-25 21:22:04.326",
      "steam_id": "76561198065774641",
      "username": "BetoJin",
      "x": "12501",
      "y": "3457",
      "z": "0",
      "hours_survived": 585,
      "event_type": "level_up",
      "skill": "MetalWelding",
      "level": "2"
    },
    {
      "timestamp": "29-12-25 21:28:52.524",
      "steam_id": "76561198065774641",
      "username": "BetoJin",
      "x": "12509",
      "y": "3444",
      "z": "0",
      "hours_survived": 588,
      "event_type": "level_up",
      "skill": "MetalWelding",
      "level": "3"
    },
    {
      "timestamp": "29-12-25 21:58:54.063",
      "steam_id": "76561198065774641",
      "username": "BetoJin",
      "x": "12513",
      "y": "3447",
      "z": "0",
      "hours_survived": 590,
      "event_type": "login",
      "skills": {
        "Cooking": 1,
        "Fitness": 10,
        "Strength": 10,
        "Blunt": 0,
        "Axe": 6,
        "Lightfoot": 0,
        "Nimble": 1,
        "Sprinting": 3,
        "Sneak": 0,
        "Woodwork": 7,
        "Aiming": 0,
        "Reloading": 0,
        "Farming": 0,
        "Fishing": 0,
        "Trapping": 1,
        "PlantScavenging": 0,
        "Doctor": 1,
        "Electricity": 2,
        "Blacksmith": 0,
        "MetalWelding": 3,
        "Mechanics": 1,
        "Spear": 0,
        "Maintenance": 4,
        "SmallBlade": 0,
        "LongBlade": 0,
        "SmallBlunt": 0,
        "Tailoring": 0,
        "Tracking": 0,
        "Husbandry": 0,
        "FlintKnapping": 0,
        "Masonry": 0,
        "Pottery": 0,
        "Carving": 0,
        "Butchering": 0,
        "Glassmaking": 0
      }
    },
    {
      "timestamp": "29-12-25 22:02:35.768",
      "steam_id": "76561199511597958",
      "username": "RottenPotato",
      "x": "12023",
      "y": "2594",
      "z": "0",
      "hours_survived": 307,
      "event_type": "login",
      "skills": {
        "Cooking": 0,
        "Fitness": 10,
        "Strength": 10,
        "Blunt": 0,
        "Axe": 4,
        "Lightfoot": 0,
        "Nimble": 0,
        "Sprinting": 2,
        "Sneak": 0,
        "Woodwork": 4,
        "Aiming": 0,
        "Reloading": 1,
        "Farming": 0,
        "Fishing": 0,
        "Trapping": 0,
        "PlantScavenging": 0,
        "Doctor": 0,
        "Electricity": 2,
        "Blacksmith": 0,
        "MetalWelding": 0,
        "Mechanics": 0,
        "Spear": 0,
        "Maintenance": 4,
        "SmallBlade": 0,
        "LongBlade": 0,
        "SmallBlunt": 0,
        "Tailoring": 0,
        "Tracking": 0,
        "Husbandry": 0,
        "FlintKnapping": 0,
        "Masonry": 3,
        "Pottery": 0,
        "Carving": 0,
        "Butchering": 0,
        "Glassmaking": 0
      }
    },
    {
      "timestamp": "29-12-25 22:29:32.150",
      "steam_id": "76561198065774641",
      "username": "admin",
      "x": "12030",
      "y": "2587",
      "z": "0",
      "hours_survived": 47,
      "event_type": "login",
      "skills": {
        "Cooking": 2,
        "Fitness": 5,
        "Strength": 5,
        "Blunt": 0,
        "Axe": 0,
        "Lightfoot": 0,
        "Nimble": 0,
        "Sprinting": 0,
        "Sneak": 0,
        "Woodwork": 0,
        "Aiming": 0,
        "Reloading": 0,
        "Farming": 0,
        "Fishing": 0,
        "Trapping": 0,
        "PlantScavenging": 0,
        "Doctor": 0,
        "Electricity": 0,
        "Blacksmith": 0,
        "MetalWelding": 0,
        "Mechanics": 0,
        "Spear": 0,
        "Maintenance": 1,
        "SmallBlade": 1,
        "LongBlade": 0,
        "SmallBlunt": 0,
        "Tailoring": 0,
        "Tracking": 0,
        "Husbandry": 0,
        "FlintKnapping": 0,
        "Masonry": 0,
        "Pottery": 0,
        "Carving": 0,
        "Butchering": 0,
        "Glassmaking": 0
      }
    },
    {
      "timestamp": "29-12-25 22:41:38.537",
      "steam_id": "76561198065774641",
      "username": "admin",
      "x": "11783",
      "y": "3606",
      "z": "0",
      "hours_survived": 51,
      "event_type": "login",
      "skills": {
        "Cooking": 2,
        "Fitness": 5,
        "Strength": 5,
        "Blunt": 0,
        "Axe": 0,
        "Lightfoot": 0,
        "Nimble": 0,
        "Sprinting": 0,
        "Sneak": 0,
        "Woodwork": 0,
        "Aiming": 0,
        "Reloading": 0,
        "Farming": 0,
        "Fishing": 0,
        "Trapping": 0,
        "PlantScavenging": 0,
        "Doctor": 0,
        "Electricity": 0,
        "Blacksmith": 0,
        "MetalWelding": 0,
        "Mechanics": 0,
        "Spear": 0,
        "Maintenance": 1,
        "SmallBlade": 1,
        "LongBlade": 0,
        "SmallBlunt": 0,
        "Tailoring": 0,
        "Tracking": 0,
        "Husbandry": 0,
        "FlintKnapping": 0,
        "Masonry": 0,
        "Pottery": 0,
        "Carving": 0,
        "Butchering": 0,
        "Glassmaking": 0
      }
    },
    {
      "timestamp": "29-12-25 22:43:46.492",
      "steam_id": "76561199511597958",
      "username": "RottenPotato",
      "x": "12023",
      "y": "2593",
      "z": "0",
      "hours_survived": 316,
      "event_type": "login",
      "skills": {
        "Cooking": 0,
        "Fitness": 10,
        "Strength": 10,
        "Blunt": 0,
        "Axe": 4,
        "Lightfoot": 0,
        "Nimble": 0,
        "Sprinting": 2,
        "Sneak": 0,
        "Woodwork": 4,
        "Aiming": 0,
        "Reloading": 1,
        "Farming": 0,
        "Fishing": 0,
        "Trapping": 0,
        "PlantScavenging": 0,
        "Doctor": 0,
        "Electricity": 2,
        "Blacksmith": 0,
        "MetalWelding": 0,
        "Mechanics": 0,
        "Spear": 0,
        "Maintenance": 4,
        "SmallBlade": 0,
        "LongBlade": 0,
        "SmallBlunt": 0,
        "Tailoring": 0,
        "Tracking": 0,
        "Husbandry": 0,
        "FlintKnapping": 0,
        "Masonry": 3,
        "Pottery": 0,
        "Carving": 0,
        "Butchering": 0,
        "Glassmaking": 0
      }
    }
  ],
  "chat_messages": [],
  "timestamp": "2025-12-29T23:00:01.410936"
}